djadmin_export/__init__.py
djadmin_export/models.py
djadmin_export/register.py
djadmin_export/utils.py
djadmin_export/exporters/__init__.py
djadmin_export/exporters/base.py
djadmin_export/exporters/xlsx.py
djadmin_export-0.2.0.dist-info/DESCRIPTION.rst
djadmin_export-0.2.0.dist-info/METADATA
djadmin_export-0.2.0.dist-info/RECORD
djadmin_export-0.2.0.dist-info/WHEEL
djadmin_export-0.2.0.dist-info/metadata.json
djadmin_export-0.2.0.dist-info/top_level.txt
